docserver.py
docserver-0.2.1.dist-info/entry_points.txt
docserver-0.2.1.dist-info/LICENSE
docserver-0.2.1.dist-info/WHEEL
docserver-0.2.1.dist-info/METADATA
docserver-0.2.1.dist-info/RECORD
