Metadata-Version: 2.1
Name: docserver
Version: 0.2.1
Summary: A PyPI-style documentation server.
Home-page: https://github.com/kgaughan/docserver
License: UNKNOWN
Author: Keith Gaughan
Author-email: k@stereochro.me
Requires-Python: >=3.3
Classifier: Environment :: Web Environment
Classifier: Intended Audience :: Developers
Classifier: License :: OSI Approved :: Apache Software License
Classifier: Operating System :: OS Independent
Classifier: Programming Language :: Python :: 2.7
Classifier: Topic :: Internet :: WWW/HTTP :: WSGI :: Application
Requires-Dist: humanize
Requires-Dist: pystache
Requires-Dist: werkzeug>=0.15
